wafec_tests_openstack_testware-1.0.3-py3.8-nspkg.pth
wafec_tests_openstack_testware/_configuration.py
wafec_tests_openstack_testware/base.py
wafec_tests_openstack_testware/base_tests.py
wafec_tests_openstack_testware/exceptions.py
wafec_tests_openstack_testware/glance.py
wafec_tests_openstack_testware/interception_agent.py
wafec_tests_openstack_testware/interception_controller.py
wafec_tests_openstack_testware/interception_model.py
wafec_tests_openstack_testware/interception_service.py
wafec_tests_openstack_testware/logon.py
wafec_tests_openstack_testware/neutron.py
wafec_tests_openstack_testware/nova.py
wafec_tests_openstack_testware/nova_tests.py
wafec_tests_openstack_testware/types.py
wafec_tests_openstack_testware/types_tests.py
wafec_tests_openstack_testware/utils.py
wafec_tests_openstack_testware/command_line/__init__.py
wafec_tests_openstack_testware/command_line/_base.py
wafec_tests_openstack_testware/command_line/interception.py
wafec_tests_openstack_testware/command_line/main.py
wafec_tests_openstack_testware-1.0.3.dist-info/METADATA
wafec_tests_openstack_testware-1.0.3.dist-info/WHEEL
wafec_tests_openstack_testware-1.0.3.dist-info/entry_points.txt
wafec_tests_openstack_testware-1.0.3.dist-info/namespace_packages.txt
wafec_tests_openstack_testware-1.0.3.dist-info/top_level.txt
wafec_tests_openstack_testware-1.0.3.dist-info/RECORD
