Metadata-Version: 2.1
Name: wafec-tests-openstack-testware
Version: 1.0.3
Summary: UNKNOWN
Home-page: UNKNOWN
Author: Wallace
Author-email: wallacefcardoso@gmail.com
License: UNKNOWN
Platform: UNKNOWN
Classifier: Programming Language :: Python :: 3
Classifier: License :: OSI Approved :: MIT License
Classifier: Operating System :: OS Independent
Requires-Dist: python-novaclient (>=17.2.1)
Requires-Dist: python-glanceclient (>=3.2.2)
Requires-Dist: python-neutronclient (>=7.2.1)
Requires-Dist: python-keystoneclient (>=4.1.1)
Requires-Dist: Flask (>=1.1.2)
Requires-Dist: SQLAlchemy (>=1.3.20)
Requires-Dist: PyMySQL (>=0.10.1)
